{
  "ru": {
    "BS-AK": "Аклинс",
    "BS-BI": "Бимини",
    "BS-BP": "Блэк-Пойнт",
    "BS-BY": "Берри",
    "BS-CE": "Центральный Эльютера",
    "BS-CI": "Кэт",
    "BS-CK": "Крукед-Айленд",
    "BS-CO": "Центральный Абако",
    "BS-CS": "Центральный Андрос",
    "BS-EG": "Восточный Большой Багама",
    "BS-EX": "Эксума",
    "BS-FP": "Фрипорт",
    "BS-GC": "Гранд Ки",
    "BS-HI": "Остров Харбор",
    "BS-HT": "Хоуп-Таун",
    "BS-IN": "Инагуа",
    "BS-LI": "Лонг-Айленд",
    "BS-MC": "Мангров-Ки",
    "BS-MG": "Маягуана",
    "BS-MI": "Морес",
    "BS-NE": "Северный Эльютера",
    "BS-NO": "Северный Абако",
    "BS-NP": "Нью-Провиденс",
    "BS-NS": "Северный Андрос",
    "BS-RC": "Рам-Ки",
    "BS-RI": "Рэггид-Айленд",
    "BS-SA": "Южный Андрос",
    "BS-SE": "Южный Эльютера",
    "BS-SO": "Южный Абако",
    "BS-SS": "Сан-Сальвадор",
    "BS-SW": "Спэниш-Уэллс",
    "BS-WG": "Западный Большой Багама"
  },
  "de": {
    "BS-BP": "Black Point, Bahamas",
    "BS-HI": "Harbour Island, Bahamas",
    "BS-SS": "San Salvador"
  },
  "fr": {
    "BS-BI": "Îles Bimini",
    "BS-BY": "Îles Berry",
    "BS-CI": "Île Cat",
    "BS-EX": "Îles Exumas",
    "BS-SS": "San Salvador"
  },
  "es": {
    "BS-BY": "Islas Berry",
    "BS-CI": "Isla Cat",
    "BS-CK": "Isla de Crooked",
    "BS-HI": "Isla Harbour",
    "BS-LI": "Isla Larga",
    "BS-MC": "Cayo Mangrove",
    "BS-MI": "Isla de Moore",
    "BS-NE": "Eleuthera Norte",
    "BS-NO": "Ábaco Norte",
    "BS-NP": "Nueva Providencia",
    "BS-NS": "Andros Norte",
    "BS-RC": "Cayo Rum",
    "BS-RI": "Isla Ragged",
    "BS-SA": "Andros Sur",
    "BS-SE": "Eleuthera Sur",
    "BS-SS": "San Salvador"
  },
  "zh": {
    "BS-AK": "阿克林岛",
    "BS-BP": "Black Point, Bahamas",
    "BS-CI": "卡特島",
    "BS-CK": "克魯克德島",
    "BS-FP": "Freeport, Bahamas",
    "BS-HI": "哈勃岛",
    "BS-LI": "長島",
    "BS-MG": "馬亞瓜納島",
    "BS-NP": "新普罗维登斯岛",
    "BS-RI": "拉吉德岛",
    "BS-SS": "圣萨尔瓦多岛"
  },
  "hi": {
    "BS-BP": "Black Point, Bahamas",
    "BS-CI": "Cat Island, Bahamas",
    "BS-CK": "Crooked Island, Bahamas",
    "BS-FP": "Freeport, Bahamas",
    "BS-HI": "Harbour Island, Bahamas",
    "BS-LI": "Long Island, Bahamas"
  },
  "pt": {
    "BS-BP": "Black Point, Bahamas",
    "BS-CI": "Cat Island, Bahamas",
    "BS-CK": "Crooked Island, Bahamas",
    "BS-FP": "Freeport, Bahamas",
    "BS-HI": "Harbour Island, Bahamas",
    "BS-LI": "Long Island, Bahamas"
  },
  "ja": {
    "BS-BP": "Black Point, Bahamas",
    "BS-CI": "Cat Island, Bahamas",
    "BS-CK": "Crooked Island, Bahamas",
    "BS-FP": "Freeport, Bahamas",
    "BS-HI": "Harbour Island, Bahamas",
    "BS-LI": "Long Island, Bahamas"
  },
  "ar": {
    "BS-BP": "Black Point, Bahamas",
    "BS-CI": "Cat Island, Bahamas",
    "BS-CK": "Crooked Island, Bahamas",
    "BS-FP": "فريبورت",
    "BS-HI": "Harbour Island, Bahamas",
    "BS-LI": "Long Island, Bahamas",
    "BS-NP": "بروفيدانس الجديدة"
  },
  "it": {
    "BS-CI": "Cat",
    "BS-IN": "Great Inagua",
    "BS-SS": "San Salvador"
  },
  "he": {
    "BS-BP": "Black Point, Bahamas",
    "BS-CI": "Cat Island, Bahamas",
    "BS-CK": "Crooked Island, Bahamas",
    "BS-FP": "Freeport, Bahamas",
    "BS-HI": "Harbour Island, Bahamas",
    "BS-LI": "Long Island, Bahamas"
  }
}
