{
  "ru": {
    "CY-01": "Никосия",
    "CY-02": "Лимасол",
    "CY-03": "Ларнака",
    "CY-04": "Фамагуста",
    "CY-05": "Пафос",
    "CY-06": "Кирения"
  },
  "de": {
    "CY-01": "Bezirk Nikosia",
    "CY-02": "Bezirk Limassol",
    "CY-03": "Bezirk Larnaka",
    "CY-04": "Bezirk Famagusta",
    "CY-05": "Bezirk Paphos",
    "CY-06": "Bezirk Kyrenia"
  },
  "fr": {
    "CY-01": "District de Nicosie",
    "CY-02": "District de Limassol",
    "CY-03": "District de Larnaca",
    "CY-04": "District de Famagouste",
    "CY-05": "District de Paphos",
    "CY-06": "District de Kyrenia"
  },
  "es": {
    "CY-01": "Distrito de Nicosia",
    "CY-02": "Distrito de Limasol",
    "CY-03": "Distrito de Lárnaca",
    "CY-04": "Distrito de Famagusta",
    "CY-05": "Distrito de Pafos",
    "CY-06": "Distrito de Kyrenia"
  },
  "zh": {
    "CY-06": "凯里尼亚区"
  },
  "ar": {
    "CY-01": "منطقة نيقوسيا",
    "CY-02": "منطقة ليماسول",
    "CY-03": "منطقة لارنكا",
    "CY-04": "منطقة فاماغوستا",
    "CY-05": "منطقة بافوس",
    "CY-06": "منطقة كيرينيا"
  },
  "it": {
    "CY-01": "Distretto di Nicosia",
    "CY-02": "Distretto di Limassol",
    "CY-03": "Distretto di Larnaca",
    "CY-04": "Distretto di Famagosta",
    "CY-05": "Distretto di Pafo",
    "CY-06": "Distretto di Kyrenia"
  }
}
