{
  "ru": {
    "VC-01": "Шарлотта",
    "VC-06": "Гренадины"
  },
  "de": {
    "VC-01": "Charlotte Parish, Saint Vincent and the Grenadines"
  },
  "fr": {
    "VC-01": "Charlotte",
    "VC-06": "Grenadines"
  },
  "es": {
    "VC-01": "Carlota"
  },
  "zh": {
    "VC-01": "夏洛特区",
    "VC-06": "格瑞那丁區"
  },
  "hi": {
    "VC-01": "Charlotte Parish, Saint Vincent and the Grenadines"
  },
  "pt": {
    "VC-01": "Charlotte Parish, Saint Vincent and the Grenadines"
  },
  "ja": {
    "VC-01": "Charlotte Parish, Saint Vincent and the Grenadines"
  },
  "ar": {
    "VC-01": "Charlotte Parish, Saint Vincent and the Grenadines"
  },
  "it": {
    "VC-01": "Parrocchia di Charlotte",
    "VC-06": "Parrocchia delle Grenadine"
  },
  "he": {
    "VC-01": "Charlotte Parish, Saint Vincent and the Grenadines"
  }
}
