{
  "LY-BA": "Benghazi",
  "LY-BU": "Butnan",
  "LY-DR": "Derna",
  "LY-GT": "Ghat",
  "LY-JA": "Jabal al Akhdar",
  "LY-JG": "Jabal al Gharbi",
  "LY-JI": "Jafara",
  "LY-JU": "Jufra",
  "LY-KF": "Kufra",
  "LY-MB": "Murqub",
  "LY-MI": "Misrata",
  "LY-MJ": "Marj",
  "LY-MQ": "Murzuq",
  "LY-NL": "Nalut",
  "LY-NQ": "Nuqat al Khams",
  "LY-SB": "Sabha",
  "LY-SR": "Sirte",
  "LY-TB": "Tripoli",
  "LY-WA": "Al Wahat",
  "LY-WD": "Wadi al Hayaa",
  "LY-WS": "Wadi al Shatii",
  "LY-ZA": "Zawiya"
}
